toolspro/__init__.py
toolspro/tools.py
toolspro/util.py
toolsPro-0.0.2.dist-info/LICENSE
toolsPro-0.0.2.dist-info/METADATA
toolsPro-0.0.2.dist-info/WHEEL
toolsPro-0.0.2.dist-info/top_level.txt
toolsPro-0.0.2.dist-info/RECORD
