Metadata-Version: 2.1
Name: toolsPro
Version: 0.0.2
Summary: toolsPro
Home-page: https://gitee.com/daben_chen/pro-pip-tools
Author: guhao
Author-email: guhao@pin-dao.cn
License: MIT
Platform: UNKNOWN
Classifier: License :: OSI Approved :: MIT License
Classifier: Programming Language :: Python
Classifier: Programming Language :: Python :: 3
Requires-Python: >=3.6.8
Requires-Dist: yagmail
